{
  //Name this cinfiguration
"name": "Codespace for Skills!",
  //Using the base code space image 
"image": "mcr.microsoft.com/vscode/devcontainers/universal:latest",

  "remoteUser" : "codespace",
  "overrideCommand": false,

  //Add the IDs of extensions you want to install when the cotainer is created.
  "customization":{
    "vsscode": {
      "extension": [
        "GitHub.copilot"
      ]
    }
  }
   ,
 "postCreateCommand": "echo '# Writing code upon codespace creation!'  >> codespace.md"
}
